Metadata-Version: 1.0
Name: basic-dists-prob-lib
Version: 0.1
Summary: Gaussian distributions
Home-page: UNKNOWN
Author: Patrick Hofmann
Author-email: UNKNOWN
License: UNKNOWN
Platform: UNKNOWN
